{
    "type": "silentgear:tip",
    "stats": {
        "enchantability": {
            "mul2": 0.1
        },
        "harvest_speed": {
            "mul2": 0.4
        },
        "melee_damage": {
            "add": 2
        },
        "magic_damage": {
            "add": 2
        },
        "ranged_speed": {
            "mul2": 0.3
        },
        "rarity": 10
    },
    "traits": [
        {
            "name": "silentgear:refractive",
            "level": 1
        },
        {
            "name": "silentgear:lustrous",
            "level": 4
        }
    ],
    "crafting_items": {
        "normal": {
            "item": "silentgear:glowstone_coated_upgrade"
        }
    },
    "name": {
        "translate": "part.silentgear.tip.glowstone"
    },
    "textures": {
        "all": {
            "lite_texture": "high_contrast",
            "texture_suffix": "glowstone",
            "normal_color": "white",
            "fallback_color": "#D2D200"
        }
    },
    "availability": {
        "gear_blacklist": []
    }
}
