{
  "type": "silentgear:simple",
  "parent": "silentgear:empty",
  "crafting": {
    "can_salvage": true,
    "categories": [
      "organic",
      "fiber",
      "basic"
    ],
    "gear_type_blacklist": [],
    "ingredient": {
      "item": "silentgear:fluffy_string"
    },
    "part_substitutes": {}
  },
  "display": {
    "color": "#FFFFFAE5",
    "main_texture_type": "LOW_CONTRAST",
    "name": {
      "translate": "material.silentgear.fluffy_string"
    },
    "name_prefix": ""
  },
  "properties": {
    "silentgear:binding": {
      "armor_durability": {
        "operation": "MULTIPLY_BASE",
        "value": 0.05
      },
      "harvest_speed": {
        "operation": "MULTIPLY_BASE",
        "value": -0.05
      },
      "traits": [
        {
          "conditions": [],
          "level": 3,
          "trait": "silentgear:flexible"
        }
      ]
    },
    "silentgear:cord": {
      "draw_speed": {
        "operation": "MULTIPLY_BASE",
        "value": -0.05
      },
      "ranged_damage": {
        "operation": "MULTIPLY_BASE",
        "value": 0.05
      }
    }
  }
}