{
  "availability": {
    "tier": 2,
    "categories": [
      "gem"
    ],
    "visible": true,
    "gear_blacklist": [],
    "can_salvage": true
  },
  "crafting_items": {
    "main": {
      "tag": "forge:gems/quartz"
    }
  },
  "name": {
    "translate": "material.silentgear.quartz"
  },
  "stats": {
    "main": {
      "durability": 330.0,
      "armor_durability": 13.0,
      "enchantability": 10.0,
      "harvest_level": 2.0,
      "harvest_speed": 7.0,
      "melee_damage": 2.0,
      "magic_damage": 0.0,
      "attack_speed": 0.1,
      "armor": 14.0,
      "armor/helmet": 3.0,
      "armor/chestplate": 5.0,
      "armor/leggings": 4.0,
      "armor/boots": 2.0,
      "magic_armor": 4.0,
      "ranged_damage": 0.0,
      "ranged_speed": 0.1,
      "projectile_speed": 1.0,
      "projectile_accuracy": 1.0,
      "rarity": 40.0,
      "chargeability": 1.2
    },
    "rod": {
      "durability": {
        "mul2": -0.2
      },
      "harvest_speed": {
        "mul2": 0.2
      },
      "melee_damage": {
        "mul2": 0.1
      },
      "rarity": 30.0
    },
    "tip": {
      "durability": {
        "add": 64.0
      },
      "armor_durability": {
        "add": 64.0
      },
      "harvest_level": {
        "max": 2.0
      },
      "harvest_speed": {
        "add": 2.0
      },
      "melee_damage": {
        "add": 4.0
      },
      "ranged_damage": {
        "add": 1.5
      },
      "rarity": {
        "add": 20.0
      }
    },
    "adornment": {}
  },
  "traits": {
    "main": [
      {
        "name": "silentgear:crushing",
        "level": 3
      },
      {
        "name": "silentgear:jagged",
        "level": 2
      }
    ],
    "rod": [
      {
        "name": "silentgear:brittle",
        "level": 2
      }
    ],
    "tip": [
      {
        "name": "silentgear:chipping",
        "level": 1
      },
      {
        "name": "silentgear:jagged",
        "level": 3
      }
    ],
    "adornment": [
      {
        "name": "silentgear:mighty",
        "level": 2,
        "conditions": [
          {
            "type": "silentgear:material_ratio",
            "ratio": 0.5
          }
        ]
      }
    ]
  }
}