{
    "type": "silentgear:gear_crafting",
    "group": "silentgear:pickaxes",
    "ingredients": [
        {
            "tag": "silentgear:blueprints/pickaxe"
        },
        {
            "type": "silentgear:part_type",
            "part_type": "main"
        },
        {
            "type": "silentgear:part_type",
            "part_type": "main"
        },
        {
            "type": "silentgear:part_type",
            "part_type": "main"
        }
    ],
    "result": {
        "item": "silentgear:pickaxe"
    }
}
