{
  "parent": "silentgear:crimson_repair_kit",
  "criteria": {
    "get_item": {
      "conditions": {
        "items": [
          {
            "items": [
              "silentgear:azure_repair_kit"
            ]
          }
        ]
      },
      "trigger": "minecraft:inventory_changed"
    }
  },
  "display": {
    "announce_to_chat": true,
    "description": {
      "translate": "advancements.silentgear.azure_repair_kit.description"
    },
    "frame": "task",
    "hidden": false,
    "icon": {
      "item": "silentgear:azure_repair_kit"
    },
    "show_toast": true,
    "title": {
      "translate": "advancements.silentgear.azure_repair_kit.title"
    }
  },
  "requirements": [
    [
      "get_item"
    ]
  ],
  "sends_telemetry_event": true
}