{
  "type": "minecraft:chest",
  "pools": [
    {
      "bonus_rolls": {
        "type": "minecraft:uniform",
        "max": 1.0,
        "min": 0.0
      },
      "entries": [
        {
          "type": "minecraft:empty",
          "weight": 10
        },
        {
          "type": "minecraft:item",
          "functions": [
            {
              "add": false,
              "count": {
                "type": "minecraft:uniform",
                "max": 2.0,
                "min": 1.0
              },
              "function": "minecraft:set_count"
            }
          ],
          "name": "silentgear:netherwood_sapling",
          "weight": 20
        },
        {
          "type": "minecraft:item",
          "functions": [
            {
              "add": false,
              "count": {
                "type": "minecraft:uniform",
                "max": 4.0,
                "min": 2.0
              },
              "function": "minecraft:set_count"
            }
          ],
          "name": "silentgear:nether_banana",
          "weight": 10
        },
        {
          "type": "minecraft:item",
          "name": "silentgear:golden_nether_banana"
        }
      ],
      "rolls": {
        "type": "minecraft:uniform",
        "max": 2.0,
        "min": 1.0
      }
    }
  ]
}